Metadata-Version: 1.0
Name: gas-bin-distribution
Version: 0.1
Summary: Gaussian and Binomial distributions
Home-page: UNKNOWN
Author: Simon Peter Ofula Amoth
Author-email: simonofula@gmail.com
License: UNKNOWN
Platform: UNKNOWN
